LICENSE
MANIFEST.in
README.rst
pytest_gae.py
setup.py
pytest_gae.egg-info/PKG-INFO
pytest_gae.egg-info/SOURCES.txt
pytest_gae.egg-info/dependency_links.txt
pytest_gae.egg-info/entry_points.txt
pytest_gae.egg-info/top_level.txt