Metadata-Version: 1.1
Name: pytest-gae
Version: 0.2.2
Summary: pytest plugin for apps written with Google's AppEngine
Home-page: http://bitbucket.org/petraszd/pytest_gae/
Author: Petras Zdanavicius (petraszd)
Author-email: petraszd@gmail.com
License: MIT License
Keywords: py.test pytest google app engine
Platform: UNKNOWN
Classifier: Development Status :: 3 - Alpha
Classifier: Intended Audience :: Developers
Classifier: License :: OSI Approved :: MIT License
Classifier: Programming Language :: Python :: 2
Classifier: Topic :: Software Development :: Testing
Requires: pytest
